jing/__init__.py
jing/data_center.py
jing/downloader_aker.py
jing/downloader_baostock.py
jing/downloader_bn.py
jing/downloader_entrance.py
jing/downloader_yahooer.py
jing/rule_container.py
jing/rule_each.py
jing/rule_regression.py
jing/stock_reference.py
jing/stock_tech.py
jing/stock_trend.py
jing/util_config.py
jing/util_file_set.py
jing/util_log.py
jing/util_meta.py
jing/x.py
jing/y.py
jing/z.py
jing-0.2.7.dist-info/METADATA
jing-0.2.7.dist-info/WHEEL
jing-0.2.7.dist-info/top_level.txt
jing-0.2.7.dist-info/RECORD
