Metadata-Version: 2.4
Name: jing
Version: 0.2.7
Summary: Download stock data and perform data analisys
Author-email: sai <sai@gmail.com>
License: MIT
Keywords: jing,sai,stock
Classifier: Programming Language :: Python :: 3
Classifier: License :: OSI Approved :: MIT License
Classifier: Operating System :: OS Independent
Requires-Dist: requests
Requires-Dist: importlib-metadata; python_version < "3.10"
